Workbook

Sheet Sheet1
A1: Checknumber | B1: ChunkID | C1: Speaker | D1: Label | E1: Count | F1: Start time | G1: End time | H1: WAV_Link | I1: Valid | J1: Reason | K1: Close to | L1: Glued | M1: Other DF | N1: Multi-FP | O1: FP-length | P1: Struct. cont. | Q1: Dis. type | R1: Anneliese, HELP! | S1: ManualCorrectionOrtho | T1: Word2Word | U1: Phrase | V1: PCOMP | W1: vorn_valid4exp | X1: vorn_mit | Y1: vorn_ohne | Z1: hinten_valid4exp | AA1: hinten_mit | AB1: hinten_ohne | AC1: ganz_valid4exp | AD1: ganz_ohne | AE1: ganz_mit
A2: 4 | C2: 001M | D2: äh | E2: 004 | F2: 488.143 | G2: 497.586 | H2: file:///C:/TI_projekt_daten/Audio/001M_äh_004.wav | I2: no | J2: not a FP | S2: äh = die? | U2: ja ich meine es ist schon ein bisschen hügelig aber viele Berge also richtige Berge die sind auch äh sind weiter weg als da in Graz [ die ] hm
A3: 9 | C3: 001M | D3: äh | E3: 009 | F3: 2618.002 | G3: 2629.517 | H3: file:///C:/TI_projekt_daten/Audio/001M_äh_009.wav | I3: no | J3: short FP | U3: das ist übrigens ich glaube das <*ENG>C (+ $N + $N +) hat so eine Liste auf seiner <*ENG>Homepage <breathingIN> da ist so bei den äh bei den , #fünfzehn interessantesten Gebäuden der [ Welt oben oder ] Architekturen ja
A4: 17 | C4: 001M | D4: ahm | E4: 008 | F4: 3584.796 | G4: 3593.238 | H4: file:///C:/TI_projekt_daten/Audio/001M_ahm_008.wav | I4: no | J4: other df | L4: no | M4: no | N4: no | O4: mid | P4: no | Q4: 2 | T4: vor ein paar Jahren waren ahm haben wir (+ in + in +) Oberösterreich | U4: [ genau apropos Sonnenflecken ] <breathingIN> irgendwann auf ein <&b>p vor ein paar Jahren waren ahm haben wir (+ in + in +) Oberösterreich haben wir Nord=Lichter gesehen [ das war ziemlich <*ENG>cool ]
A5: 10 | C5: 001M | D5: ahm | E5: 001 | F5: 297.108 | G5: 305.594 | H5: file:///C:/TI_projekt_daten/Audio/001M_ahm_001.wav | I5: no | J5: answer | U5: <smack> <breathingIN> <noise> [ boah <breathingOUT> ] <breathingIN> <noise> ahm ja grundsätzlich schon <breathingIN> aber ein bisschen mehr Hügel hätte ich gerne es ist mir zu flach | V5: <breathingIN><smack><breathingIN> <noise> change <breathingOUT> <breathingIN> <noise> hes hold hold <breathingIN> hold hold
A6: 3 | B6: 001M_462.1_Typ1 | C6: 001M | D6: äh | E6: 003 | F6: 460.452 | G6: 469.638 | H6: file:///C:/TI_projekt_daten/Audio/001M_äh_003.wav | I6: yes | L6: back | M6: no | N6: no | O6: mid | P6: yes | Q6: 1 | T6: es wäre dort eine interessante äh Firma gewesen | U6: naja sagen wir so also nach Innsbruck wollte ich nicht aber die es wäre dort eine interessante äh Firma gewesen also sagen wir { <breathingIN> } [ ja eigentlich ] | W6: 1 | X6: super | Y6: super | Z6: 1 | AB6: super
A7: 1 | C7: 001M | D7: äh | E7: 001 | F7: 363.385 | G7: 371.768 | H7: file:///C:/TI_projekt_daten/Audio/001M_äh_001.wav | I7: no | J7: not enough speech | U7: [ <laughter> ] [ <laughter> ] <breathingIN> [ äh ] <noise> <smack>nein [ <noise> ja ] schon [ oder ] so
A8: 2 | C8: 001M | D8: äh | E8: 002 | F8: 396.672 | G8: 405.012 | H8: file:///C:/TI_projekt_daten/Audio/001M_äh_002.wav | I8: no | J8: not enough speech | U8: <breathingIN> naja <&L>Wochenendhaus { <noise> } [ <laughter> ] { <breathingIN> } äh [ achso ] [ mhm ]
A9: 5 | C9: 001M | D9: äh | E9: 005 | F9: 585.763 | G9: 595.46 | H9: file:///C:/TI_projekt_daten/Audio/001M_äh_005.wav | I9: no | J9: answer | U9: die öffentlichen Verkehrsmittel <&L>deswegen <&L>fahre <&L>ich <&L>immer <&L>mit <&L>dem <&L>Rad { <breathingIN> } äh ja weil alles #drei mal so lange dauert
A10: 12 | C10: 001M | D10: ahm | E10: 003 | F10: 825.475 | G10: 834.044 | H10: file:///C:/TI_projekt_daten/Audio/001M_ahm_003.wav | I10: no | L10: no | M10: yes | N10: no | O10: long | P10: maybe | T10: und dann ahm naja habe ich halt erfahren | U10: aufgescheuchten <*DIAL>Hendeln <breathingIN> [ <laughter> ] <breathingIN> und dann ahm naja habe ich halt erfahren dass er <breathingIN> dass er <#noise> eben die Klausur ist { <breathingIN> }
A11: 6 | C11: 001M | D11: äh | E11: 006 | F11: 889.11 | G11: 897.408 | H11: file:///C:/TI_projekt_daten/Audio/001M_äh_006.wav | I11: no | J11: not enough speech | U11: [ mhm ] [ <laughter> ] { <breathingIN> } [ äh ] [ naja ]
A12: 7 | C12: 001M | D12: äh | E12: 007 | F12: 1030.259 | G12: 1038.558 | H12: file:///C:/TI_projekt_daten/Audio/001M_äh_007.wav | I12: no | J12: not enough speech | U12: [ <laughter> ] <breathingIN> [ äh ] { <breathingIN> } [ mhm ] { <noise> } [ ja keine Ahnung also ]
A13: 8 | C13: 001M | D13: äh | E13: 008 | F13: 1463.072 | G13: 1471.334 | H13: file:///C:/TI_projekt_daten/Audio/001M_äh_008.wav | I13: no | J13: double talk | U13: Hundeüberrest <&L>dann <&L>herumliegen ist [ <&L>dann <&L>auch <&L>schon <&L>Wurst ] { <breathingIN> } [ äh ] { <noise> } ah stimmt [ ja ] mhm
A14: 13 | C14: 001M | D14: ahm | E14: 004 | F14: 1539.479 | G14: 1547.84 | H14: file:///C:/TI_projekt_daten/Audio/001M_ahm_004.wav | I14: no | J14: other df | U14: du <*DIAL>deppert mhm [ ja aber weil_du ] das sagst { <noise> } [ ahm ] { <breathingIN> } <noise> [ <noise> unsere ] Kinder haben irgendwie in letzter Zeit so Vorlieben also interessieren sich halt für Weltraum und Sterne
A15: 14 | C15: 001M | D15: ahm | E15: 005 | F15: 1553.385 | G15: 1562.532 | H15: file:///C:/TI_projekt_daten/Audio/001M_ahm_005.wav | I15: no | J15: long pause | K15: 15 | L15: no | M15: yes | N15: no | O15: long | T15: und dann hab ich gelesen dass ahm die ah ich glaube jedes Jahr zwanzigtausend ahm Steine aus dem Weltraum auf die Erde fallen | U15: und halt auch Meteoriten <breathingIN> (+ und + und +) so und dann habe ich gelesen dass ahm <noise> die <#noise> ah ich glaube <noise>
A16: 16 | C16: 001M | D16: ahm | E16: 007 | F16: 1646.078 | G16: 1655.324 | H16: file:///C:/TI_projekt_daten/Audio/001M_ahm_007.wav | I16: no | J16: double talk | U16: [ mhm ] [ mhm ] [ ja ahm das stimmt ja ] [ mhm ] { <breathingIN> } { <noise> } [ genau ] [ mhm ]
A17: 18 | C17: 002M | D17: äh | E17: 001 | F17: 234.184 | G17: 243.37 | H17: file:///C:/TI_projekt_daten/Audio/002M_äh_001.wav | I17: no | J17: double talk | U17: { <breathingIN> } [ mhm ] <breathingOUT> <noise> Münzgrabenstraße ist auch nicht so schön <breathingOUT> { <breathingIN> } [ äh Hötzendorfstraße ] [ <smack> <breathingIN> ] [ ja das stimmt ] <breathingOUT> { <noise> } { <#noise> } { <breathingIN> } | V17: <noise> <smack> <breathingIN> hrt <breathingOUT> <noise> change_hold <breathingOUT> <breathingIN> hes change <breathingIN><smack><breathingIN> part_hold@ change <breathingOUT> <noise> <breathingIN> hrt
A18: 38 | C18: 002M | D18: ähm | E18: 001 | F18: 264.679 | G18: 273.822 | H18: file:///C:/TI_projekt_daten/Audio/002M_ähm_001.wav | I18: no | J18: not enough speech | U18: [ was ein Kanal ? ] { <breathingOUT> } [ ja Kanal ] ja stimmt geh <&b>we oh schön <breathingIN> ähm Gewässer { <breathingOUT> } <breathingIN> [ da haben wir ] auch nur (+ sehr + sehr +) [ wenige ] in [ Graz ] { <breathingIN> } | V18: hold_question hold_question <breathingOUT> hold hold part_hold@ hold part_hold@ disruption@ hold hold <breathingIN> hes hold <breathingOUT> <breathingIN> cont change <breathingIN> part
A19: 23 | C19: 002M | D19: äh | E19: 006 | F19: 1517.608 | G19: 1525.969 | H19: file:///C:/TI_projekt_daten/Audio/002M_äh_006.wav | I19: no | J19: long pause | U19: ein ziemlich großer Stein <breathingOUT> <breathingIN> so groß zirka wie <breathingIN> äh <breathingOUT> puh jetzt muss ich einmal überlegen
A20: 28 | C20: 002M | D20: äh | E20: 011 | F20: 2067.444 | G20: 2076.109 | H20: file:///C:/TI_projekt_daten/Audio/002M_äh_011.wav | I20: no | J20: name | U20: <noise> naja { <breathingIN> } uh ja Hader ist gut ja <breathingIN> äh <breathingIN> ich habe gesehen die <*ENG>science <*ENG>busters [ im Orpheum ]
A21: 29 | C21: 002M | D21: äh | E21: 012 | F21: 2223.244 | G21: 2231.868 | H21: file:///C:/TI_projekt_daten/Audio/002M_äh_012.wav | I21: no | J21: need more | K21: 30 | U21: nein kein Sauerteig { <breathingIN> } (+ äh + äh +) normales Roggenbrot ja halt so [ äh ] <&b>Trockeng genau
A22: 30 | C22: 002M | D22: äh | E22: 013 | F22: 2226.667 | G22: 2235.201 | H22: file:///C:/TI_projekt_daten/Audio/002M_äh_013.wav | I22: no | J22: other df | K22: 29 | U22: { <breathingIN> } (+ äh + äh +) normales Roggenbrot ja halt so [ äh ] <&b>Trockeng genau Trockengerm [ Trockenhefe ] oh ja das es geht schon
A23: 41 | C23: 002M | D23: ähm | E23: 004 | F23: 2266.697 | G23: 2275.025 | H23: file:///C:/TI_projekt_daten/Audio/002M_ähm_004.wav | I23: no | J23: rare word | U23: [ im Englischen ] heißt es <*ENG>the <*ENG>sour <*ENG>dough [ finde ich sehr nett ] { <breathingIN> } [ ja egal ] <breathingIN> [ ähm ] da haben wir einen Hermannkuchen gemacht [ kennst_du einen Hermannkuchen ] <breathingIN> da wurde der Sauerteig vor zig Jahren einmal
A24: 32 | C24: 002M | D24: äh | E24: 015 | F24: 2760.3 | G24: 2768.768 | H24: file:///C:/TI_projekt_daten/Audio/002M_äh_015.wav | I24: no | J24: short after | U24: die haben ja eh den ein oder anderen Bach der durch Graz geht [ unterirdisch ] [ äh ] fließen lassen der
A25: 35 | C25: 002M | D25: äh | E25: 018 | F25: 3365.113 | G25: 3373.619 | H25: file:///C:/TI_projekt_daten/Audio/002M_äh_018.wav | I25: no | J25: name | U25: was war deine Frage was man da so [ macht in ] Marwiesen auf [ so einem Truppenübungsplatz ] <breathingIN> äh <breathingIN> Gefechte simulieren
A26: 31 | C26: 002M | D26: äh | E26: 014 | F26: 2296.353 | G26: 2304.895 | H26: file:///C:/TI_projekt_daten/Audio/002M_äh_014.wav | I26: no | J26: not a FP | U26: [ verbreitet ja ] <breathingIN> aber ich bin mir sicher dass es die Steirer auch drauf haben [ ich mein ob ] sie es drauf haben [ äh ] { <breathingIN> } [ bin ich mir nicht sicher aber sie werden es vielleicht schon einmal gehört ] haben [ ja ]
A27: 42 | C27: 002M | D27: ähm | E27: 005 | F27: 3375.801 | G27: 3384.921 | H27: file:///C:/TI_projekt_daten/Audio/002M_ähm_005.wav | I27: no | J27: double talk | U27: Gefechte [ du lernst ] bitte [ nein ähm ] nein Knallmunition [ ja ]
A28: 44 | C28: 003M | D28: äh | E28: 001 | F28: 44.61 | G28: 53.15 | H28: file:///C:/TI_projekt_daten/Audio/003M_äh_001.wav | I28: no | J28: disruption at wrong point | L28: no | M28: yes | N28: no | O28: mid | P28: yes | R28: x | T28: und da sehe ich so von der Ferne äh erste Stra okay also erste Straßenbahn fährt weg | U28: bin ich zur Keplerbrücke gegangen <breathingOUT> <smack> <breathingIN> und da sehe ich so von der Ferne <breathingIN> äh <breathingOUT><smack> <smack> <breathingIN> erste <&b>Stra ok Straßenbahn fährt weg denke ich mir ok die nächste kommt dann in #vier oder #fünf Minuten | V28: hold <breathingOUT> <smack> <breathingIN> disruption hold hold hold hold <breathingIN>
A29: 11 | C29: 001M | D29: ahm | E29: 002 | F29: 783.333 | G29: 792.049 | H29: file:///C:/TI_projekt_daten/Audio/001M_ahm_002.wav | I29: yes | J29: pause und aber da weg | L29: no | M29: no | N29: no | O29: long | P29: new | Q29: 4 | T29: das war ganz witzig aber da ahm ja ich weiß nicht | U29: ja <&b>f das war ganz witzig <noise> [ aber ] <noise> da <noise> ahm <breathingOUT> <breathingIN> ja ich weiß nicht das hat irgendwie
A30: 70 | C30: 003M | D30: ähm | E30: 001 | F30: 205.93 | G30: 214.527 | H30: file:///C:/TI_projekt_daten/Audio/003M_ähm_001.wav | I30: no | J30: disruption at wrong point | L30: no | M30: yes | N30: no | O30: long | P30: maybe | T30: der nimmt meine ähm mein direkt mein mein Stimmbandsignal auf | U30: der nimmt meine <noise> <smack> <breathingIN> ähm <breathingOUT> <breathingIN> mein direkt mein <breathingIN> mein Stimmbandsignal auf | V30: disruption change <breathingIN><smack><breathingIN>
A31: 52 | C31: 003M | D31: äh | E31: 009 | F31: 732.736 | G31: 744.659 | H31: file:///C:/TI_projekt_daten/Audio/003M_äh_009.wav | I31: no | J31: rare word | U31: [ nein ] ahm <smack> wie ist das eigentlich bei Narkolepsie ist das <&b>ver verbunden mit äh anderen Beeinträchtigungen [ oder ] <*DIAL>knackst einfach manchmal weg
A32: 55 | C32: 003M | D32: äh | E32: 012 | F32: 905.95 | G32: 914.526 | H32: file:///C:/TI_projekt_daten/Audio/003M_äh_012.wav | I32: no | J32: short after | U32: ich hoffe ich war bin nicht zu ah <smack> wie sagt man äh ja also
A33: 71 | C33: 003M | D33: ähm | E33: 002 | F33: 1992.474 | G33: 2001.596 | H33: file:///C:/TI_projekt_daten/Audio/003M_ähm_002.wav | I33: no | J33: hard to understand | U33: aber jedenfalls der Andreas und ich haben heute auch schon geredet über eine Couch wir brauchen auch unbedingt [ eine Couch im ] jetzt in <&b>uns ähm unserem Büro
A34: 68 | C34: 003M | D34: äh | E34: 025 | F34: 2951.748 | G34: 2962.364 | H34: file:///C:/TI_projekt_daten/Audio/003M_äh_025.wav | I34: no | J34: double talk | U34: [ mhm ] { <smack> } [ aber das ] ist bei dem schon klar gewesen dass das [ äh ] <noise> dass wie das funktioniert #S#
A35: 47 | C35: 003M | D35: äh | E35: 004 | F35: 216.192 | G35: 224.949 | H35: file:///C:/TI_projekt_daten/Audio/003M_äh_004.wav | I35: no | J35: not enough speech | U35: [ <breathingIN> <smack> <breathingIN> ] { <smack> } <smack> äh <#noise> <breathingIN> <#noise> <breathingIN><smack><breathingIN> hm man erkennt die Grundfrequenz (+ von + von +) der Sprache direkter | V35: <breathingIN><smack><breathingIN> <smack> <smack> hes <breathingIN> <breathingIN><smack><breathingIN> hold cont cont
A36: 74 | C36: 003M | D36: ahm | E36: 002 | F36: 288.122 | G36: 296.708 | H36: file:///C:/TI_projekt_daten/Audio/003M_ahm_002.wav | I36: no | J36: initial FP | U36: <breathingOUT> <smack> <noise> { <breathingIN> } { <breathingOUT> } [ <breathingIN><smack><breathingIN> ] ahm <smack> ja der hat da eben Sprache aufgenommen <breathingOUT> [ also ] | V36: <breathingOUT> <smack> <noise> <breathingIN> <breathingOUT> <breathingIN><smack><breathingIN> hes <smack> hold hold <breathingOUT> @disruption <breathingIN>
A37: 51 | C37: 003M | D37: äh | E37: 008 | F37: 684.399 | G37: 693.62 | H37: file:///C:/TI_projekt_daten/Audio/003M_äh_008.wav | I37: no | J37: rare word | U37: <smack> <breathingIN> [ Hypnotherapie ] ist das äh Schlaftherapie
A38: 76 | C38: 003M | D38: ahm | E38: 004 | F38: 731.315 | G38: 740.126 | H38: file:///C:/TI_projekt_daten/Audio/003M_ahm_004.wav | I38: no | J38: initial FP | U38: [ nein ] ahm <smack> wie ist das eigentlich bei Narkolepsie ist das <&b>ver verbunden mit äh
A39: 53 | C39: 003M | D39: äh | E39: 010 | F39: 838.49 | G39: 850.099 | H39: file:///C:/TI_projekt_daten/Audio/003M_äh_010.wav | I39: no | J39: short FP | U39: welcher Zweite <smack> <breathingIN> ah seine äh der seine #drei #viertel Kilo Tortellini [ gegessen hat ] das war der Hannes ja
A40: 54 | C40: 003M | D40: äh | E40: 011 | F40: 869.081 | G40: 878.083 | H40: file:///C:/TI_projekt_daten/Audio/003M_äh_011.wav | I40: no | J40: initial FP | U40: das ist jetzt peinlich [ hm ] äh <smack> wir könnten irgendwie , Gott fragen
A41: 56 | C41: 003M | D41: äh | E41: 013 | F41: 981.118 | G41: 991.52 | H41: file:///C:/TI_projekt_daten/Audio/003M_äh_013.wav | I41: no | J41: initial FP | U41: [ äh ] ich bin mir nicht ganz sicher aber ich glaube sie haben sie [ mitgebracht ] [ hm ]
A42: 77 | C42: 003M | D42: ahm | E42: 005 | F42: 1077.739 | G42: 1086.433 | H42: file:///C:/TI_projekt_daten/Audio/003M_ahm_005.wav | I42: no | J42: answer | U42: <breathingIN> <breathingOUT> <smack> ahm nein #S#
A43: 58 | C43: 003M | D43: äh | E43: 015 | F43: 1293.536 | G43: 1302.171 | H43: file:///C:/TI_projekt_daten/Audio/003M_äh_015.wav | I43: no | J43: initial FP | U43: äh ein Hundehalsband [ hm ]
A44: 15 | B44: 001M_1562.75_Typ1 | C44: 001M | D44: ahm | E44: 006 | F44: 1562.541 | G44: 1570.868 | H44: file:///C:/TI_projekt_daten/Audio/001M_ahm_006.wav | I44: yes | K44: 14 | L44: back | M44: no | N44: no | O44: mid | P44: yes | Q44: 1 | T44: ich glaube jedes Jahr zwanzigtausend ahm Steine aus dem Weltraum auf die Erde fallen | U44: ah ich glaube <noise> jedes Jahr #zwanzigtausend ahm [ Steine ] aus_dem Weltraum auf die Erde [ fallen ] ohne dass sie verglühen also das wirklich | X44: das, was du rausgeschnitten hast (double filler) braucht mehr rauschen | Z44: 1 | AC44: 1 | AD44: das, was du rausgeschnitten hast (double filler) braucht mehr rauschen | AE44: das, was du rausgeschnitten hast (double filler) braucht mehr rauschen
A45: 59 | C45: 003M | D45: äh | E45: 016 | F45: 1747.29 | G45: 1757.841 | H45: file:///C:/TI_projekt_daten/Audio/003M_äh_016.wav | I45: no | L45: both | M45: no | N45: no | O45: long | P45: maybe | T45: das heißt ihr müsst eigentlich Wer äh Werbung designen | U45: [ hm <breathingIN> ] das heißt ihr müsst eigentlich <&b>Wer [ äh ] Werbung <*ENG>designen für die [ Frühförderung ] das hört sich ein bisschen dubios an [ hm ]
A46: 60 | C46: 003M | D46: äh | E46: 017 | F46: 2052.795 | G46: 2062.089 | H46: file:///C:/TI_projekt_daten/Audio/003M_äh_017.wav | I46: no | J46: initial FP | U46: ich habe dich gefragt wozu braucht man eine Couch am Arbeitsplatz <smack> [ <&b>nei äh ] um sich #zehn <&b>viertelstun #zehn Minuten Viertelstunde nach dem Essen dort [ hinzulegen ]
A47: 62 | C47: 003M | D47: äh | E47: 019 | F47: 2253.21 | G47: 2261.815 | H47: file:///C:/TI_projekt_daten/Audio/003M_äh_019.wav | I47: no | J47: initial FP | U47: ja äh unsere Couch deine [ Couch ]
A48: 63 | C48: 003M | D48: äh | E48: 020 | F48: 2499.352 | G48: 2508.264 | H48: file:///C:/TI_projekt_daten/Audio/003M_äh_020.wav | I48: no | J48: double talk | U48: ja , wir haben gezeigt dass es möglich ist ja nochmal wozu [ ist es gut <breathingIN> ] ja man kann die Fenster so anordnen wie man will und äh { <breathingOUT> } [ <breathingIN> das Gebäude steht eigentlich ] äh ah besteht auf
A49: 65 | C49: 003M | D49: äh | E49: 022 | F49: 2759.623 | G49: 2769.544 | H49: file:///C:/TI_projekt_daten/Audio/003M_äh_022.wav | I49: no | J49: spelling | U49: das ist glaube ich teilweise für das Dirha Projekt was wir gerade machen äh $D $I $R $H $A <breathingIN> <*ENG>Distance<breathingIN> <*ENG>Recognition nein ich weiß nicht
A50: 69 | C50: 003M | D50: äh | E50: 026 | F50: 3392.087 | G50: 3401.684 | H50: file:///C:/TI_projekt_daten/Audio/003M_äh_026.wav | I50: no | J50: rare word | U50: es verschwimmt ein bisschen ja [ also ] ok äh Lord Eddard Stark enthauptet <&b>vo vom ah
A51: 96 | C51: 004M | D51: äh | E51: 001 | F51: 190.47 | G51: 200.659 | H51: file:///C:/TI_projekt_daten/Audio/004M_äh_001.wav | I51: no | J51: broken word | U51: { <breathingOUT> } <breathingIN> [ deswegen kennen ] sie auch [ beide die Viki . ] <breathingOUT> { <breathingOUT> } { <smack> } { <breathingIN> } [ und dass der <&b>wf ] Stevie mir das von der <&b>kri äh <noise> Viki Geschichte erzählt hat das haben wir eh geredet ge <breathingOUT> <breathingIN>
A52: 103 | C52: 004M | D52: ahm | E52: 003 | F52: 1248.135 | G52: 1256.783 | H52: file:///C:/TI_projekt_daten/Audio/004M_ahm_003.wav | I52: no | J52: rare word | L52: no | M52: no | N52: no | O52: long | P52: new | Q52: 4 | T52: [ erbaut ] lassen vom Sixtus dem Sechsten [ oder ] Fünften <breathingIN> ahm ja und | U52: [ erbaut ] lassen vom Sixtus dem Sechsten [ oder ] Fünften <breathingIN> ahm ja und
A53: 19 | B53: 002M_311.62_Typ1 | C53: 002M | D53: äh | E53: 002 | F53: 308.28 | G53: 316.677 | H53: file:///C:/TI_projekt_daten/Audio/002M_äh_002.wav | I53: yes | L53: no | M53: no | N53: no | O53: mid | P53: yes | Q53: 1 | T53: wie heißt äh der Bezirk wo du wohnst | U53: naja stimmt stimmt <breathingIN> wie heißt äh der Bezirk wo du wohnst <&b>Lieben ach blöd [ genau ] stimmt Liebenau heißt [ das ] | W53: 1 | Z53: 1 | AC53: 2 | AD53: pause zu leise
A54: 98 | C54: 004M | D54: äh | E54: 003 | F54: 1421.918 | G54: 1430.327 | H54: file:///C:/TI_projekt_daten/Audio/004M_äh_003.wav | I54: no | J54: rare word | U54: das sind so die sich in Interimspäpste wo sie gedacht haben äh wir wissen jetzt nicht genau wohin wir gehen
A55: 105 | C55: 004M | D55: ahm | E55: 005 | F55: 2112.81 | G55: 2121.209 | H55: file:///C:/TI_projekt_daten/Audio/004M_ahm_005.wav | I55: no | J55: other df | U55: [ nein ] aber ich finde ihn nicht schlecht ahm das ist ah <&b>sp also es sind voll super Schauspieler dabei
A56: 109 | C56: 004M | D56: ahm | E56: 009 | F56: 3088.464 | G56: 3096.952 | H56: file:///C:/TI_projekt_daten/Audio/004M_ahm_009.wav | I56: no | J56: long pause | U56: kein Dunkelblau das ihr aus wo du nie weißt ob das jetzt schwarz ist oder dunkelblau sondern so ein <#artefact> ahm Dunkelblau einfach so ein (+ Blau + [ Blau ] +)
A57: 102 | C57: 004M | D57: ahm | E57: 002 | F57: 1179.89 | G57: 1188.422 | H57: file:///C:/TI_projekt_daten/Audio/004M_ahm_002.wav | I57: no | J57: initial FP | U57: [ <laughter> ] ahm naja es ist nichts anderes als jeder andere [ Monarch ]
A58: 20 | C58: 002M | D58: äh | E58: 003 | F58: 953.314 | G58: 961.866 | H58: file:///C:/TI_projekt_daten/Audio/002M_äh_003.wav | I58: yes | L58: no | M58: yes | N58: no | O58: mid | P58: yes | Q58: 1 | T58: nein aber äh die wild Kiwis steirische Kiwis | U58: gesehen habe [ <&L>nein ] { <breathingIN> } das ist ein [ Blödsinn ] { <breathingIN> } <noise> [ nein aber ] äh die wild Kiwis [ steirische ] Kiwis die [ sind ganz ]
A59: 104 | C59: 004M | D59: ahm | E59: 004 | F59: 1374.579 | G59: 1382.988 | H59: file:///C:/TI_projekt_daten/Audio/004M_ahm_004.wav | I59: no | J59: initial FP | U59: auf [ <laughter> ] ahm aber seit warte lass mich überlegen
A60: 106 | C60: 004M | D60: ahm | E60: 006 | F60: 2119.596 | G60: 2129.619 | H60: file:///C:/TI_projekt_daten/Audio/004M_ahm_006.wav | I60: no | J60: name | U60: <&b>sp also es sind voll super Schauspieler dabei also der Tom Hanks der ahm Hugo Weaving ahm <breathingIN> die Susan Sarandon spielt noch mit glaube ich
A61: 107 | C61: 004M | D61: ahm | E61: 007 | F61: 2122.871 | G61: 2131.518 | H61: file:///C:/TI_projekt_daten/Audio/004M_ahm_007.wav | I61: no | J61: name | U61: also der Tom Hanks der ahm Hugo Weaving ahm <breathingIN> die Susan Sarandon spielt noch mit glaube ich
A62: 108 | C62: 004M | D62: ahm | E62: 008 | F62: 2132.467 | G62: 2141.61 | H62: file:///C:/TI_projekt_daten/Audio/004M_ahm_008.wav | I62: no | J62: name | U62: dann der eben der Ben Whishaw <noise> [ ahm ] und noch ein paar
A63: 99 | C63: 004M | D63: äh | E63: 004 | F63: 2241.982 | G63: 2251.098 | H63: file:///C:/TI_projekt_daten/Audio/004M_äh_004.wav | I63: no | J63: other df | U63: das sind nur so einzelne Geschichten (+ wo sie + wo sie +) sich einmal wo sie sich gegenseitig umbringen und <breathingIN> [ das ] [ äh nein ] nein ich weiß <breathingIN> aber er war echt
A64: 100 | C64: 004M | D64: äh | E64: 005 | F64: 2419.579 | G64: 2429.85 | H64: file:///C:/TI_projekt_daten/Audio/004M_äh_005.wav | I64: no | J64: rare word | U64: nein eh aber jetzt spielt es nirgends mehr { <breathingIN> } du (+ äh + äh +) Fun hat Dings gekriegt was ist (+ [ Emmy ] + Emmy +) nein oder was ist gestern verliehen worden ?
A65: 21 | C65: 002M | D65: äh | E65: 004 | F65: 1266.36 | G65: 1274.989 | H65: file:///C:/TI_projekt_daten/Audio/002M_äh_004.wav | I65: yes | L65: no | M65: no | N65: no | O65: mid | P65: maybe | Q65: 1 | R65: listen | T65: Graz sage ich äh nur so im Grünbereich | U65: { <noise> } das wäre da in Graz einmal [ notwendig ] Graz sage ich äh <noise> nur so im Grünbereich weil [ stell dir ] vor <breathingIN> die Hunde <*DIAL>gackseln da jetzt alles voll
A66: 534 | C66: 005M | D66: ähm | E66: 002 | F66: 751.664 | G66: 760.963 | H66: file:///C:/TI_projekt_daten/Audio/005M_ähm_002.wav | I66: no | J66: other df | U66: naja ich meine ein bisschen schräg musst <&b>scho glaube ich schon sein (+ es ist schon + es ist schon +) weit ziemlich abstrakt wir haben letztens geredet ähm (+ beim + beim +) (+ mit + mit +) meiner Trainingsrunde halt über die | V66: hrt
A67: 535 | C67: 005M | D67: ähm | E67: 003 | F67: 945.668 | G67: 954.391 | H67: file:///C:/TI_projekt_daten/Audio/005M_ähm_003.wav | I67: no | J67: und äh | U67: ja genau das ist bei uns auch so üblich ne <breathingIN> und ähm <breathingOUT> das ist auch irgendwie so ein das ist so ein Absatz und das ist so | V67: cont hold q-part <breathingIN><smack><breathingIN> disruption hold <noise> <smack> cont disruption_incomplete
A68: 512 | C68: 005M | D68: äh | E68: 002 | F68: 1015.494 | G68: 1027.136 | H68: file:///C:/TI_projekt_daten/Audio/005M_äh_002.wav | I68: no | J68: other df | K68: 852 | U68: [ hm ] { <breathingOUT> } [ ok ] { <breathingOUT> } { <smack> } { <breathingIN> } <smack> aber äh <&b>versch kommst du dort dann relativ leicht mit oder ist das relativ [ ist das ] interessant schon | V68: hrt <breathingOUT> hrt <breathingOUT> <smack> <breathingIN> <smack> hold_question disruption_question question hrt cont_question
A69: 536 | C69: 005M | D69: ähm | E69: 004 | F69: 1123.323 | G69: 1133.169 | H69: file:///C:/TI_projekt_daten/Audio/005M_ähm_004.wav | I69: no | J69: other df | U69: überlegen ob ich mir das auf (+ meinen + meinen +) Spracherwerb in Spanisch [ anwenden <&b>k ] <noise> ähm ich habe (+ meinen + meinen +) Urlaub fix gemacht <noise> ich fahre im achso nein warte habe ich dir eh geschrieben oder | V69: hold <laughter> <breathingIN><smack><breathingIN> hes hold <noise> <breathingIN> <smack> disruption <breathingOUT> part@ part part_hold@ hold q-part <smack>
A70: 22 | C70: 002M | D70: äh | E70: 005 | F70: 1443.709 | G70: 1455.127 | H70: file:///C:/TI_projekt_daten/Audio/002M_äh_005.wav | I70: yes | J70: glued | L70: back | M70: no | N70: no | O70: mid | P70: yes | Q70: 1 | T70: weil das ist äh moralisch ja nicht vertretbar das Ganze | U70: [ Schussapparat ja ] naja <breathingIN> nein das ist<breathingIN> wir machen [ natürlich jetzt ] nur Scherze weil [ das ist <breathingIN> äh moralisch ja nicht vertretbar das Ganze ] ja aber [ man könnte ] [ <&L>trete <&L>mich <laughter> ] { <breathingIN> } [ Tretminen <&L>legen ]
A71: 513 | C71: 005M | D71: äh | E71: 003 | F71: 1200.633 | G71: 1209.248 | H71: file:///C:/TI_projekt_daten/Audio/005M_äh_003.wav | I71: no | J71: not enough speech | U71: [ aber <breathingOUT> ] <noise> <breathingIN> äh [ <?> ] | V71: disruption
A72: 514 | C72: 005M | D72: äh | E72: 004 | F72: 1535.431 | G72: 1545.901 | H72: file:///C:/TI_projekt_daten/Audio/005M_äh_004.wav | I72: no | J72: other df | U72: <noise> ich meinst ah hält das mit das äh in letzter Zeit ein Musikvideo geschickt , wahrscheinlich nicht oder
A73: 515 | C73: 005M | D73: äh | E73: 005 | F73: 1614.187 | G73: 1623.043 | H73: file:///C:/TI_projekt_daten/Audio/005M_äh_005.wav | I73: no | J73: not enough speech | U73: das hilft [ <breathingIN> schreibst ] du jetzt eigentlich wirklich an also schon der Dis [ <&b>un ] also (+ bei + bei +) dem Sinn äh Veröffentlichung sind die bei euch Deutsch oder ? #S#
A74: 516 | C74: 005M | D74: äh | E74: 006 | F74: 1710.827 | G74: 1722.224 | H74: file:///C:/TI_projekt_daten/Audio/005M_äh_006.wav | I74: no | J74: hard to understand | U74: [ genau ] #S# [ <breathingIN> <&b>a ] aber das habe ich auch unterschätzt ich habe beim , eben in Kanada war (+ das + das +) äh eine Referat gehalten mit #vierzig Minuten
A75: 517 | C75: 005M | D75: äh | E75: 007 | F75: 1836.706 | G75: 1846.925 | H75: file:///C:/TI_projekt_daten/Audio/005M_äh_007.wav | I75: no | J75: initial FP | U75: [ <noise> <#noise> ] { <breathingIN> } ja äh ich glaube es ist gar keine so gute Idee die kennst du das die Bettina ich weiß nicht nein ich glaube nicht Süd Tirolerin meine Arbeits=Kollegin
A76: 36 | B76: 002M_3481.0_Typ1 | C76: 002M | D76: äh | E76: 019 | F76: 3479.827 | G76: 3488.25 | H76: file:///C:/TI_projekt_daten/Audio/002M_äh_019.wav | I76: yes | J76: Aufzählung | L76: no | M76: no | N76: no | O76: long | P76: yes | Q76: 1 | T76: Antennen aufbauen äh in Mulden hüpfen | U76: scharfer [ Munition ] Antennen aufbauen { <breathingIN> } <noise> äh [ in Mulden hüpfen ] [ ja genau ich war Kurzwellenfunker ] | W76: 1 | Z76: 1 | AC76: 1 | AD76: ggf. ist pause zu lang | AE76: ggf. ist pause zu lang
A77: 537 | C77: 005M | D77: ähm | E77: 005 | F77: 1846.659 | G77: 1855.563 | H77: file:///C:/TI_projekt_daten/Audio/005M_ähm_005.wav | I77: no | J77: other df | K77: 518 | U77: Tirolerin meine Arbeits=Kollegin nein ok <breathingIN> die ähm und äh eben ist Italienerin ne ich habe gemeint sie hat schon gewählt aber sie hat mittlerweile
A78: 518 | C78: 005M | D78: äh | E78: 008 | F78: 1848.441 | G78: 1858.384 | H78: file:///C:/TI_projekt_daten/Audio/005M_äh_008.wav | I78: no | J78: other df | K78: 537 | U78: nein ok <breathingIN> die ähm und äh eben ist Italienerin ne ich habe gemeint sie hat schon gewählt aber sie hat mittlerweile <breathingIN> liest sie keine Zeitungen mehr und schaut keine Nachrichten mehr weil sie hält die italienische Politik nicht aus
A79: 519 | C79: 005M | D79: äh | E79: 009 | F79: 1945.463 | G79: 1955.767 | H79: file:///C:/TI_projekt_daten/Audio/005M_äh_009.wav | I79: no | J79: hard to understand | U79: <breathingIN> wohl weißt eben beim Papa war äh eine Woche Ski Fahren (+ in + in +) Tirol Mitte oah die Fotos da sind einfach die Fotos vom Lift schon eine Frechheit
A80: 520 | C80: 005M | D80: äh | E80: 010 | F80: 2127.778 | G80: 2139.411 | H80: file:///C:/TI_projekt_daten/Audio/005M_äh_010.wav | I80: no | J80: short FP | U80: <breathingIN> ja [ da gibt es aber in Spanisch ] gibt es das in Italienisch mit den direkten und indirekten <&b>be äh Becktronomen ? mit den [ <&b>direk ] aber da gibt es ja auch einen #dritten #vierten Fall nicht
A81: 521 | C81: 005M | D81: äh | E81: 011 | F81: 2160.229 | G81: 2170.208 | H81: file:///C:/TI_projekt_daten/Audio/005M_äh_011.wav | I81: no | J81: hard to understand | U81: weil die ganzen Wörter so kurz sind und alle so gleich klingen ist <*DIAL>wurscht ob jetzt die äh echte wer sie ist [ irgendwas ] #S# und ob es dann #dritter oder #vierter Fall ist und dann ist es noch rückbezüglich und er ihm sie
A82: 538 | C82: 005M | D82: ähm | E82: 006 | F82: 2226.443 | G82: 2234.887 | H82: file:///C:/TI_projekt_daten/Audio/005M_ähm_006.wav | I82: no | J82: hard to understand | K82: 539 | U82: ok ein bisschen herumfragen was es gibt <breathingIN> ähm beim und Besuch nehmen <noise> ähm Patrick und San Sebastian
A83: 25 | C83: 002M | D83: äh | E83: 008 | F83: 1666.284 | G83: 1675.383 | H83: file:///C:/TI_projekt_daten/Audio/002M_äh_008.wav | I83: yes | J83: "im" almost not there | L83: no | M83: no | N83: no | O83: mid | P83: yes | Q83: 1 | T83: dass die mit einem Raumschiff äh im Weltall geflogen sind | U83: { <noise> } ja im Grunde ist so <breathingOUT> dass die mit einem Raumschiff <breathingIN> äh im Weltall geflogen [ sind und ] irgendeinen Meteoriten <breathingIN> ähm
A84: 539 | C84: 005M | D84: ähm | E84: 007 | F84: 2229.371 | G84: 2237.948 | H84: file:///C:/TI_projekt_daten/Audio/005M_ähm_007.wav | I84: no | J84: name | K84: 538 | U84: ein bisschen herumfragen was es gibt <breathingIN> ähm beim und Besuch nehmen <noise> ähm Patrick und San Sebastian und Donostia <laughter>
A85: 522 | C85: 005M | D85: äh | E85: 012 | F85: 2237.305 | G85: 2246.156 | H85: file:///C:/TI_projekt_daten/Audio/005M_äh_012.wav | I85: no | J85: und äh | U85: und Donostia <laughter> da passt genau ja <breathingIN> und äh dann ist <?> ist in der Nähe
A86: 540 | C86: 005M | D86: ähm | E86: 008 | F86: 2337.914 | G86: 2348.295 | H86: file:///C:/TI_projekt_daten/Audio/005M_ähm_008.wav | I86: no | J86: initial FP | U86: { <noise> } { <breathingIN> } ähm (+ wie +) , (+ wie +) ist denn das mit dem #S# mit dem Bericht oder so irgendwas musst da <&b>mu musst nein du musst irgendwann fertig sein oder so irgendwie [ wie geht das ]
A87: 523 | C87: 005M | D87: äh | E87: 013 | F87: 2420.331 | G87: 2428.829 | H87: file:///C:/TI_projekt_daten/Audio/005M_äh_013.wav | I87: no | J87: initial FP | U87: [ <laughter> ] <breathingIN> gemein <?> <breathingIN> äh <noise> <breathingIN> und jetzt hast , irgendwie mit den Analysen Daten für mehrere <*ENG>Paper <noise>
A88: 524 | C88: 005M | D88: äh | E88: 014 | F88: 2531.314 | G88: 2541.771 | H88: file:///C:/TI_projekt_daten/Audio/005M_äh_014.wav | I88: no | J88: not enough speech | U88: wie viel Daten das hast oder wie viel Kinder hast du eigentlich [ aufgenommen ] war jetzt äh , die_du verwendest auch oder wie
A89: 525 | C89: 005M | D89: äh | E89: 015 | F89: 2586.488 | G89: 2597.132 | H89: file:///C:/TI_projekt_daten/Audio/005M_äh_015.wav | I89: no | J89: other df | U89: aber du musst nicht jetzt irgendwie (+ die + die +) Muttersprache mit <noise> äh analysieren damit_du <noise> da [ Rückschlüsse ]
A90: 526 | C90: 005M | D90: äh | E90: 016 | F90: 2683.53 | G90: 2694.792 | H90: file:///C:/TI_projekt_daten/Audio/005M_äh_016.wav | I90: no | J90: hard to understand | U90: also wenn ich , da nicht der [ was ] <breathingIN> äh warte das letzte Mal wie wir da in der Runde gesessen sind beim wo der Flo Geburtstag gehabt hat
A91: 527 | C91: 005M | D91: äh | E91: 017 | F91: 2691.953 | G91: 2700.81 | H91: file:///C:/TI_projekt_daten/Audio/005M_äh_017.wav | I91: no | J91: not enough speech | U91: beim wo der Flo Geburtstag gehabt hat im äh Grammophon mhm { <smack> } da war der Toni dabei ja der Wikinger <laughter>
A92: 528 | C92: 005M | D92: äh | E92: 018 | F92: 2728.33 | G92: 2738.206 | H92: file:///C:/TI_projekt_daten/Audio/005M_äh_018.wav | I92: no | J92: double talk | U92: ja [ <breathingIN> ah ] [ ok ] also bist (+ kein + kein + äh + äh +) Scheibe wird heißen
A93: 541 | C93: 005M | D93: ähm | E93: 009 | F93: 2734.386 | G93: 2743.435 | H93: file:///C:/TI_projekt_daten/Audio/005M_ähm_009.wav | I93: no | J93: not enough speech | U93: Scheibe wird heißen der ähm englische halt gehen <*ENG>my <*ENG>fair <*ENG>lady
A94: 26 | C94: 002M | D94: äh | E94: 009 | F94: 1683.506 | G94: 1692.228 | H94: file:///C:/TI_projekt_daten/Audio/002M_äh_009.wav | I94: yes | J94: need more | L94: no | M94: no | N94: no | O94: mid | P94: yes | Q94: 1 | T94: Sprengkopf im Meteoriteninneren äh abgelegt haben nach einer Bohrung | U94: [ Sprengkopf ] [ im Meteoriteninneren ] { <breathingIN> } äh abgelegt [ haben ] nach einer Bohrung [ ja ] <breathingIN> ja ah siehst weißt_du was in Graz noch fehlt ein Weltraumzentrum
A95: 542 | C95: 005M | D95: ähm | E95: 010 | F95: 2789.374 | G95: 2798.415 | H95: file:///C:/TI_projekt_daten/Audio/005M_ähm_010.wav | I95: no | J95: initial FP | K95: 529 | U95: <noise> er hat ein paar andere Einschläge glaube ich drin [ aber ist nicht so schlimm ] er kommt eh aus Salzburg nein ähm #S# da bei äh hm Bodensee Attersee so ein bisschen
A96: 529 | C96: 005M | D96: äh | E96: 019 | F96: 2791.501 | G96: 2801.317 | H96: file:///C:/TI_projekt_daten/Audio/005M_äh_019.wav | I96: no | J96: name | K96: 542 | U96: nein ähm #S# da bei äh hm Bodensee Attersee so ein bisschen
A97: 27 | C97: 002M | D97: äh | E97: 010 | F97: 1990.107 | G97: 2000.098 | H97: file:///C:/TI_projekt_daten/Audio/002M_äh_010.wav | I97: yes | L97: no | M97: no | N97: no | O97: mid | P97: yes | Q97: 1 | T97: dass wir allen ein bisschen äh vorsichtig gegenüber stehen nicht | U97: [ naja du unser Sonnengott hat schon dafür gesorgt dass wir , allen ein bisschen ] { <breathingIN> } [ äh vorsichtig gegenüber stehen nicht ] [ mhm ] { <breathingIN> } { <noise> } <laughter>
A98: 543 | C98: 005M | D98: ähm | E98: 011 | F98: 2812.304 | G98: 2821.526 | H98: file:///C:/TI_projekt_daten/Audio/005M_ähm_011.wav | I98: no | J98: hard to understand | U98: ja kommt [ darauf an wie ] [ achso wenn_du ] wenn_du oben [ über ] ähm über das Voralpenkreuz fährst dann schon ja mhm , genau
A99: 544 | C99: 005M | D99: ähm | E99: 012 | F99: 2973.926 | G99: 2983.115 | H99: file:///C:/TI_projekt_daten/Audio/005M_ähm_012.wav | I99: no | J99: initial FP | U99: <&L>das <&L>war <&L>es <noise> hm <noise> <breathingIN> ähm #S# und die hat eben auch gesagt sie hat echt sie war halt #zwei Wochen da nicht <breathingIN> die hat , gewaltig Probleme mit dem Dialekt
A100: 530 | C100: 005M | D100: äh | E100: 020 | F100: 3117.459 | G100: 3125.961 | H100: file:///C:/TI_projekt_daten/Audio/005M_äh_020.wav | I100: no | J100: not enough speech | U100: mhm mhm [ <noise> äh ] <noise> <breathingIN> nein gut das ist dann
...

Sheet Statistics
A1: Categories | B1: 1 | C1: 2 | D1: 3 | E1: 4
B2: =COUNTIFS(Tabelle1[[#All],[Dis. type]], B1, Tabelle1[[#All],[Valid]], "Yes") -> 92 | C2: =COUNTIFS(Tabelle1[[#All],[Dis. type]], C1, Tabelle1[[#All],[Valid]], "Yes") -> 33 | D2: =COUNTIFS(Tabelle1[[#All],[Dis. type]], D1, Tabelle1[[#All],[Valid]], "Yes") -> 2 | E2: =COUNTIFS(Tabelle1[[#All],[Dis. type]], E1, Tabelle1[[#All],[Valid]], "Yes") -> 32
A3: Valid | B3: yes | C3: no | D3: maybe
B4: =COUNTIF(Tabelle1[[#All],[Valid]], Statistics!B3) -> 167 | C4: =COUNTIF(Tabelle1[[#All],[Valid]], Statistics!C3) -> 703 | D4: =COUNTIF(Tabelle1[[#All],[Valid]], Statistics!D3) -> 0
A6: Reasons | B6: {=_xlfn.UNIQUE(Tabelle1[Reason])} -> not a FP | C6: =COUNTIFS(Tabelle1[[#All],[Reason]],Statistics!B6, Tabelle1[[#All],[Valid]], "No") -> 3 | E6: =IF($C6=0, "", B6) -> not a FP | F6: =IF($C6=0, "", C6) -> 3 | H6: {=_xlfn.SORTBY(E6:F101, F6:F101, -1)}
A7: (for no) | B7: short FP | C7: =COUNTIFS(Tabelle1[[#All],[Reason]],Statistics!B7, Tabelle1[[#All],[Valid]], "No") -> 39 | E7: =IF($C7=0, "", B7) -> short FP | F7: =IF($C7=0, "", C7) -> 39
B8: other df | C8: =COUNTIFS(Tabelle1[[#All],[Reason]],Statistics!B8, Tabelle1[[#All],[Valid]], "No") -> 198 | E8: =IF($C8=0, "", B8) -> other df | F8: =IF($C8=0, "", C8) -> 198
B9: answer | C9: =COUNTIFS(Tabelle1[[#All],[Reason]],Statistics!B9, Tabelle1[[#All],[Valid]], "No") -> 12 | E9: =IF($C9=0, "", B9) -> answer | F9: =IF($C9=0, "", C9) -> 12
B10: 0 | C10: =COUNTIFS(Tabelle1[[#All],[Reason]],Statistics!B10, Tabelle1[[#All],[Valid]], "No") -> 0 | E10: =IF($C10=0, "", B10) | F10: =IF($C10=0, "", C10)
B11: not enough speech | C11: =COUNTIFS(Tabelle1[[#All],[Reason]],Statistics!B11, Tabelle1[[#All],[Valid]], "No") -> 27 | E11: =IF($C11=0, "", B11) -> not enough speech | F11: =IF($C11=0, "", C11) -> 27
B12: double talk | C12: =COUNTIFS(Tabelle1[[#All],[Reason]],Statistics!B12, Tabelle1[[#All],[Valid]], "No") -> 74 | E12: =IF($C12=0, "", B12) -> double talk | F12: =IF($C12=0, "", C12) -> 74
B13: long pause | C13: =COUNTIFS(Tabelle1[[#All],[Reason]],Statistics!B13, Tabelle1[[#All],[Valid]], "No") -> 9 | E13: =IF($C13=0, "", B13) -> long pause | F13: =IF($C13=0, "", C13) -> 9
B14: name | C14: =COUNTIFS(Tabelle1[[#All],[Reason]],Statistics!B14, Tabelle1[[#All],[Valid]], "No") -> 25 | E14: =IF($C14=0, "", B14) -> name | F14: =IF($C14=0, "", C14) -> 25
B15: need more | C15: =COUNTIFS(Tabelle1[[#All],[Reason]],Statistics!B15, Tabelle1[[#All],[Valid]], "No") -> 3 | E15: =IF($C15=0, "", B15) -> need more | F15: =IF($C15=0, "", C15) -> 3
B16: rare word | C16: =COUNTIFS(Tabelle1[[#All],[Reason]],Statistics!B16, Tabelle1[[#All],[Valid]], "No") -> 40 | E16: =IF($C16=0, "", B16) -> rare word | F16: =IF($C16=0, "", C16) -> 40
B17: short after | C17: =COUNTIFS(Tabelle1[[#All],[Reason]],Statistics!B17, Tabelle1[[#All],[Valid]], "No") -> 8 | E17: =IF($C17=0, "", B17) -> short after | F17: =IF($C17=0, "", C17) -> 8
B18: disruption at wrong point | C18: =COUNTIFS(Tabelle1[[#All],[Reason]],Statistics!B18, Tabelle1[[#All],[Valid]], "No") -> 4 | E18: =IF($C18=0, "", B18) -> disruption at wrong point | F18: =IF($C18=0, "", C18) -> 4
B19: pause und aber da weg | C19: =COUNTIFS(Tabelle1[[#All],[Reason]],Statistics!B19, Tabelle1[[#All],[Valid]], "No") -> 0 | E19: =IF($C19=0, "", B19) | F19: =IF($C19=0, "", C19)
B20: hard to understand | C20: =COUNTIFS(Tabelle1[[#All],[Reason]],Statistics!B20, Tabelle1[[#All],[Valid]], "No") -> 49 | E20: =IF($C20=0, "", B20) -> hard to understand | F20: =IF($C20=0, "", C20) -> 49
B21: initial FP | C21: =COUNTIFS(Tabelle1[[#All],[Reason]],Statistics!B21, Tabelle1[[#All],[Valid]], "No") -> 50 | E21: =IF($C21=0, "", B21) -> initial FP | F21: =IF($C21=0, "", C21) -> 50
B22: spelling | C22: =COUNTIFS(Tabelle1[[#All],[Reason]],Statistics!B22, Tabelle1[[#All],[Valid]], "No") -> 2 | E22: =IF($C22=0, "", B22) -> spelling | F22: =IF($C22=0, "", C22) -> 2
... B57: cut out "mit"? | C57: =COUNTIFS(Tabelle1[[#All],[Reason]],Statistics!B57, Tabelle1[[#All],[Valid]], "No") -> 0 | E57: =IF($C57=0, "", B57) | F57: =IF($C57=0, "", C57)
C58: =COUNTIFS(Tabelle1[[#All],[Reason]],Statistics!B58, Tabelle1[[#All],[Valid]], "No") -> 0 | E58: =IF($C58=0, "", B58) | F58: =IF($C58=0, "", C58)
C59: =COUNTIFS(Tabelle1[[#All],[Reason]],Statistics!B59, Tabelle1[[#All],[Valid]], "No") -> 0 | E59: =IF($C59=0, "", B59) | F59: =IF($C59=0, "", C59)
C60: =COUNTIFS(Tabelle1[[#All],[Reason]],Statistics!B60, Tabelle1[[#All],[Valid]], "No") -> 0 | E60: =IF($C60=0, "", B60) | F60: =IF($C60=0, "", C60)
C61: =COUNTIFS(Tabelle1[[#All],[Reason]],Statistics!B61, Tabelle1[[#All],[Valid]], "No") -> 0 | E61: =IF($C61=0, "", B61) | F61: =IF($C61=0, "", C61)
C62: =COUNTIFS(Tabelle1[[#All],[Reason]],Statistics!B62, Tabelle1[[#All],[Valid]], "No") -> 0 | E62: =IF($C62=0, "", B62) | F62: =IF($C62=0, "", C62)
C63: =COUNTIFS(Tabelle1[[#All],[Reason]],Statistics!B63, Tabelle1[[#All],[Valid]], "No") -> 0 | E63: =IF($C63=0, "", B63) | F63: =IF($C63=0, "", C63) | H63: other df | I63: 198
C64: =COUNTIFS(Tabelle1[[#All],[Reason]],Statistics!B64, Tabelle1[[#All],[Valid]], "No") -> 0 | E64: =IF($C64=0, "", B64) | F64: =IF($C64=0, "", C64) | H64: double talk | I64: 74
C65: =COUNTIFS(Tabelle1[[#All],[Reason]],Statistics!B65, Tabelle1[[#All],[Valid]], "No") -> 0 | E65: =IF($C65=0, "", B65) | F65: =IF($C65=0, "", C65) | H65: initial FP | I65: 50
C66: =COUNTIFS(Tabelle1[[#All],[Reason]],Statistics!B66, Tabelle1[[#All],[Valid]], "No") -> 0 | E66: =IF($C66=0, "", B66) | F66: =IF($C66=0, "", C66) | H66: hard to understand | I66: 49
C67: =COUNTIFS(Tabelle1[[#All],[Reason]],Statistics!B67, Tabelle1[[#All],[Valid]], "No") -> 0 | E67: =IF($C67=0, "", B67) | F67: =IF($C67=0, "", C67) | H67: rare word | I67: 40
C68: =COUNTIFS(Tabelle1[[#All],[Reason]],Statistics!B68, Tabelle1[[#All],[Valid]], "No") -> 0 | E68: =IF($C68=0, "", B68) | F68: =IF($C68=0, "", C68) | H68: short FP | I68: 39
C69: =COUNTIFS(Tabelle1[[#All],[Reason]],Statistics!B69, Tabelle1[[#All],[Valid]], "No") -> 0 | E69: =IF($C69=0, "", B69) | F69: =IF($C69=0, "", C69) | H69: und äh | I69: 36
C70: =COUNTIFS(Tabelle1[[#All],[Reason]],Statistics!B70, Tabelle1[[#All],[Valid]], "No") -> 0 | E70: =IF($C70=0, "", B70) | F70: =IF($C70=0, "", C70) | H70: laughter | I70: 30
C71: =COUNTIFS(Tabelle1[[#All],[Reason]],Statistics!B71, Tabelle1[[#All],[Valid]], "No") -> 0 | E71: =IF($C71=0, "", B71) | F71: =IF($C71=0, "", C71) | H71: not enough speech | I71: 27
C72: =COUNTIFS(Tabelle1[[#All],[Reason]],Statistics!B72, Tabelle1[[#All],[Valid]], "No") -> 0 | E72: =IF($C72=0, "", B72) | F72: =IF($C72=0, "", C72) | H72: name | I72: 25
C73: =COUNTIFS(Tabelle1[[#All],[Reason]],Statistics!B73, Tabelle1[[#All],[Valid]], "No") -> 0 | E73: =IF($C73=0, "", B73) | F73: =IF($C73=0, "", C73) | H73: repetition | I73: 21
C74: =COUNTIFS(Tabelle1[[#All],[Reason]],Statistics!B74, Tabelle1[[#All],[Valid]], "No") -> 0 | E74: =IF($C74=0, "", B74) | F74: =IF($C74=0, "", C74) | H74: answer | I74: 12
... C101: =COUNTIFS(Tabelle1[[#All],[Reason]],Statistics!B101, Tabelle1[[#All],[Valid]], "No") -> 0 | E101: =IF($C101=0, "", B101) | F101: =IF($C101=0, "", C101) | H101: active speech | I101: 1
